weaviate/.gitignore
weaviate/__init__.py
weaviate/auth.py
weaviate/client.py
weaviate/client.pyi
weaviate/client_executor.py
weaviate/config.py
weaviate/conftest.py
weaviate/embedded.py
weaviate/error_msgs.py
weaviate/exceptions.py
weaviate/integrations.py
weaviate/logger.py
weaviate/py.typed
weaviate/retry.py
weaviate/str_enum.py
weaviate/types.py
weaviate/util.py
weaviate/validator.py
weaviate/warnings.py
weaviate/agents/__init__.py
weaviate/agents/__init__.pyi
weaviate/agents/base.pyi
weaviate/agents/utils.pyi
weaviate/agents/classes/__init__.pyi
weaviate/agents/personalization/__init__.pyi
weaviate/agents/query/__init__.pyi
weaviate/agents/transformation/__init__.pyi
weaviate/aliases/__init__.py
weaviate/aliases/alias.py
weaviate/aliases/async_.py
weaviate/aliases/async_.pyi
weaviate/aliases/executor.py
weaviate/aliases/sync.py
weaviate/aliases/sync.pyi
weaviate/backup/__init__.py
weaviate/backup/async_.py
weaviate/backup/async_.pyi
weaviate/backup/backup.py
weaviate/backup/backup_location.py
weaviate/backup/executor.py
weaviate/backup/sync.py
weaviate/backup/sync.pyi
weaviate/classes/__init__.py
weaviate/classes/aggregate.py
weaviate/classes/backup.py
weaviate/classes/batch.py
weaviate/classes/config.py
weaviate/classes/data.py
weaviate/classes/debug.py
weaviate/classes/generate.py
weaviate/classes/generics.py
weaviate/classes/init.py
weaviate/classes/query.py
weaviate/classes/rbac.py
weaviate/classes/replication.py
weaviate/classes/tenants.py
weaviate/cluster/__init__.py
weaviate/cluster/async_.py
weaviate/cluster/async_.pyi
weaviate/cluster/base.py
weaviate/cluster/models.py
weaviate/cluster/sync.py
weaviate/cluster/sync.pyi
weaviate/cluster/types.py
weaviate/cluster/replicate/__init__.py
weaviate/cluster/replicate/async_.py
weaviate/cluster/replicate/async_.pyi
weaviate/cluster/replicate/executor.py
weaviate/cluster/replicate/sync.py
weaviate/cluster/replicate/sync.pyi
weaviate/collections/__init__.py
weaviate/collections/aggregate.py
wm_weaviate_client-4.17.0.1.dist-info/licenses/LICENSE
wm_weaviate_client-4.17.0.1.dist-info/METADATA
wm_weaviate_client-4.17.0.1.dist-info/WHEEL
wm_weaviate_client-4.17.0.1.dist-info/top_level.txt
wm_weaviate_client-4.17.0.1.dist-info/RECORD
