Metadata-Version: 2.4
Name: wm-weaviate-client
Version: 4.17.0.1
Summary: A python native Weaviate client
Home-page: https://github.com/weaviate/weaviate-python-client
Author: Weaviate
Author-email: hello@weaviate.io,
License: BSD 3-clause
Project-URL: Documentation, https://weaviate-python-client.readthedocs.io
Project-URL: Source, https://github.com/weaviate/weaviate-python-client
Project-URL: Tracker, https://github.com/weaviate/weaviate-python-client/issues
Requires-Python: >=3.9
License-File: LICENSE
Requires-Dist: httpx<0.29.0,>=0.26.0
Requires-Dist: validators<1.0.0,>=0.34.0
Requires-Dist: authlib<2.0.0,>=1.2.1
Requires-Dist: pydantic<3.0.0,>=2.8.0
Requires-Dist: grpcio<1.80.0,>=1.59.5
Requires-Dist: protobuf<7.0.0,>=4.21.6
Requires-Dist: deprecation<3.0.0,>=2.1.0
Provides-Extra: agents
Requires-Dist: weaviate-agents<2.0.0,>=1.0.0; extra == "agents"
Dynamic: license-file
